{
  "whitelisted_users": [
    {
      "client_id": "11",
      "username": "",
      "discord_id": "123456789012345678",
      "discord_name": "User",
      "timestamp": "2024-01-15T14:30:00.000000",
      "status": "active"
    },
    {
      "client_id": "111",
      "username": "",
      "discord_id": "987654321098765432",
      "discord_name": "User",
      "timestamp": "2024-01-15T15:45:00.000000",
      "status": "active"
    },
    {
      "client_id": "A8402889-0U93-43VU-938N-5NN32KJ5G69B",
      "username": "",
      "discord_id": "792468382083448853",
      "discord_name": "chiron6750",
      "timestamp": "2025-12-27T21:45:28.605826",
      "status": "active"
    },
    {
      "client_id": "XX647US2-70P5-46P4-J573-KF73F85G8D19",
      "username": "",
      "discord_id": "459784671962726412",
      "discord_name": "gl3o",
      "timestamp": "2025-12-27T21:45:59.087148",
      "status": "active"
    },
    {
      "client_id": "ZUTQN0Q4-O90I-4811-904J-6D16E2371EXX",
      "username": "",
      "discord_id": "558919452826271754",
      "discord_name": "reader018465",
      "timestamp": "2025-12-27T22:29:50.793848",
      "status": "active"
    },
    {
      "client_id": "55Y47Y6R-9R28-4933-O5M9-41728594LI51",
      "username": "",
      "discord_id": "1394655251637731342",
      "discord_name": "21thmarch",
      "timestamp": "2025-12-27T23:02:39.111763",
      "status": "active"
    },
    {
      "client_id": "Y710X3S8-8P77-45QN-K6LF-2E7652G2C0X4",
      "username": "",
      "discord_id": "1450476238735933591",
      "discord_name": "z4z9",
      "timestamp": "2025-12-28T01:22:03.028014",
      "status": "active"
    },
    {
      "client_id": "Y9Y9T819-U1P5-4N86-930N-69KI0G0B522Z",
      "username": "",
      "discord_id": "1377262368626577479",
      "discord_name": "lewis05945",
      "timestamp": "2025-12-28T01:23:38.570971",
      "status": "active"
    },
    {
      "client_id": "8V287T15-W8P0-4R79-93Q3-O29312LI7HDB",
      "username": "",
      "discord_id": "1016788548906664106",
      "discord_name": "benioshua",
      "timestamp": "2025-12-28T10:13:38.471122",
      "status": "active"
    },
    {
      "client_id": "VU604U35-RP77-47M9-K06J-7GD98D85464Z",
      "username": "",
      "discord_id": "1435014215420215396",
      "discord_name": "andy_0067",
      "timestamp": "2025-12-28T10:55:04.750951",
      "status": "active"
    },
    {
      "client_id": "2106AT3S-892R-47N8-841N-OH23IG40E889",
      "username": "",
      "discord_id": "1358425921073451260",
      "discord_name": "simple_albo",
      "timestamp": "2025-12-28T12:34:46.424151",
      "status": "active"
    },
    {
      "client_id": "5WXSQ9ON-0503-4MH4-F9H5-C6A3Y3129Z96",
      "username": "",
      "discord_id": "1431020261095899157",
      "discord_name": "afkseit2019",
      "timestamp": "2025-12-28T13:18:16.905087",
      "status": "active"
    },
    {
      "client_id": "w0wt98q0-s924-49q2-k9j6-2jh1b40b294x",
      "username": "zfyzvwulw",
      "discord_id": "1309669869029163019",
      "discord_name": "ezomeprazol",
      "timestamp": "2025-12-28T16:30:48.068311",
      "status": "active"
    },
    {
      "client_id": "54A8XRU4-38P3-437P-81O4-3K088H9932H6",
      "username": "",
      "discord_id": "1362091310277984380",
      "discord_name": "fyg9",
      "timestamp": "2025-12-28T16:40:51.146144",
      "status": "active"
    },
    {
      "client_id": "5Y5680U7-9274-4UR3-ON7O-M5H7GC8Z0ZYX",
      "username": "",
      "discord_id": "1337476566078193744",
      "discord_name": "momo_4848",
      "timestamp": "2025-12-28T17:44:48.223110",
      "status": "active"
    },
    {
      "client_id": "3A0X34WT-SNL1-4507-957J-F95E630GC304",
      "username": "",
      "discord_id": "1319734715858550835",
      "discord_name": "layysi69",
      "timestamp": "2025-12-28T18:02:31.327558",
      "status": "active"
    },
    {
      "client_id": "A0TS9T42-2353-41P9-M35M-52M89I44578I",
      "username": "nvg08843",
      "discord_id": "1452783528654798859",
      "discord_name": "diepomfrits",
      "timestamp": "2025-12-28T19:03:28.354498",
      "status": "active"
    },
    {
      "client_id": "zy1u7pp7-2252-4l7j-9mg7-8fd5b4aztu64",
      "username": "",
      "discord_id": "334317123964895234",
      "discord_name": "xvcxvrsx",
      "timestamp": "2025-12-28T22:59:25.011212",
      "status": "active"
    },
    {
      "client_id": "51YY4145-R141-49R5-9OQ4-KHH977E29CBZ",
      "username": "",
      "discord_id": "1205834966936719360",
      "discord_name": "125qidigga",
      "timestamp": "2025-12-29T00:55:24.716620",
      "status": "active"
    },
    {
      "client_id": "y0y8w23p-0q63-494p-kij9-g5b4889dc4wu",
      "username": "YxodbGY",
      "discord_id": "1088547489034018836",
      "discord_name": "dexoovp",
      "timestamp": "2025-12-29T05:34:56.490360",
      "status": "active"
    },
    {
      "client_id": "7YU9UT24-5R79-4527-LO94-5432H4GG62C3",
      "username": "",
      "discord_id": "1005072184563220552",
      "discord_name": "glexo_",
      "timestamp": "2025-12-29T08:49:16.298973",
      "status": "active"
    },
    {
      "client_id": "Z713T77W-3789-4S04-N730-O66LMG5G4E6B",
      "username": "",
      "discord_id": "576789542238027786",
      "discord_name": "va9p",
      "timestamp": "2025-12-29T12:38:16.957131",
      "status": "active"
    },
    {
      "client_id": "47V2VR14-63P9-467N-9N87-0365JL7I7I6B",
      "username": "",
      "discord_id": "693743359348703253",
      "discord_name": "senisen0000",
      "timestamp": "2025-12-29T13:56:02.410778",
      "status": "active"
    },
    {
      "client_id": "1198021301361709057",
      "username": "N5U_421",
      "discord_id": "1307811647733370981",
      "discord_name": "8.u.0",
      "timestamp": "2025-12-29T14:28:20.460535",
      "status": "active"
    },
    {
      "client_id": "66X35T1S-966U-48Q3-L728-O9I12799H2E2",
      "username": "",
      "discord_id": "1051564788452446290",
      "discord_name": "interval2000",
      "timestamp": "2025-12-29T14:40:52.617157",
      "status": "active"
    },
    {
      "client_id": "Y5TW97RP-64Q4-4178-J788-K140I9IB6Z54",
      "username": "WnzaqpaMqldj18",
      "discord_id": "1191062350665625621",
      "discord_name": "bennoman_01",
      "timestamp": "2025-12-29T16:02:38.926457",
      "status": "active"
    },
    {
      "client_id": "Z2U75151-332T-48T3-N501-6L1O7MH35H01",
      "username": "SqRknNxkjaY17",
      "discord_id": "597114561174306827",
      "discord_name": "matixs.",
      "timestamp": "2025-12-29T17:04:04.818186",
      "status": "active"
    },
    {
      "client_id": "40aw8431-74uq-4qp3-k998-h84j5h469g68",
      "username": "S3gttae",
      "discord_id": "1391477136891842560",
      "discord_name": "521_impulse",
      "timestamp": "2025-12-29T20:06:51.747832",
      "status": "active"
    },
    {
      "client_id": "86075v07-626v-4u7q-n789-35l2j4li9321",
      "username": "Yndbl257643385",
      "discord_id": "1386280911913357455",
      "discord_name": "trim1000",
      "timestamp": "2025-12-29T23:32:49.451736",
      "status": "active"
    },
    {
      "client_id": "1Z0W0653-VP51-4O20-M81M-M3I7F987GB7A",
      "username": "",
      "discord_id": "1392134364837707826",
      "discord_name": "niki11111111111111",
      "timestamp": "2025-12-30T05:31:53.966027",
      "status": "active"
    },
    {
      "client_id": "VTV33Q51-2PNL-4501-9J36-927I1H67B3DC",
      "username": "",
      "discord_id": "1373338485854965842",
      "discord_name": "lyxar_banned",
      "timestamp": "2025-12-30T06:06:06.952790",
      "status": "active"
    },
    {
      "client_id": "9x786vr3-99so-4ql8-85h2-43337h6h6g66",
      "username": "oavhnylojc02",
      "discord_id": "1404713445428826152",
      "discord_name": "w1nstonchurchill",
      "timestamp": "2025-12-30T10:20:52.631668",
      "status": "active"
    },
    {
      "client_id": "7v77x6wu-1o55-4o05-893k-if5d8g8c52x0",
      "username": "",
      "discord_id": "1432383020945375364",
      "discord_name": "lenny676767",
      "timestamp": "2025-12-30T12:33:27.851092",
      "status": "active"
    },
    {
      "client_id": "Z473YTU2-R78M-4671-KM55-8IGC4361640B",
      "username": "",
      "discord_id": "964108899089272862",
      "discord_name": "cqtcher",
      "timestamp": "2025-12-30T13:56:14.022667",
      "status": "active"
    },
    {
      "client_id": "V8XS8SPQ-6283-42OL-8I88-215909FD409C",
      "username": "",
      "discord_id": "1071848778857992242",
      "discord_name": "pyxj",
      "timestamp": "2025-12-30T15:59:24.857084",
      "status": "active"
    },
    {
      "client_id": "4356Y1Y6-79TP-43P2-MK28-HI3DG326301D",
      "username": "wttdarjtju676969",
      "discord_id": "1060438336361218089",
      "discord_name": "highaura",
      "timestamp": "2025-12-30T16:53:05.529044",
      "status": "active"
    },
    {
      "client_id": "2869Z811-UU30-42T6-8475-05529QLL9HI3",
      "username": "",
      "discord_id": "1065953034892484710",
      "discord_name": "glacio_tv",
      "timestamp": "2025-12-30T17:17:49.351494",
      "status": "active"
    },
    {
      "client_id": "W04VWUP3-49LJ-40I6-GE1B-0Z69AA2Y27T6",
      "username": "",
      "discord_id": "1305899920397439093",
      "discord_name": "developer.phil",
      "timestamp": "2025-12-30T17:39:15.917911",
      "status": "active"
    },
    {
      "client_id": "A03874T5-RT35-4510-N33Q-6N56K441F084",
      "username": "gbesbdcbr",
      "discord_id": "1028300578306138142",
      "discord_name": "lindon1.",
      "timestamp": "2025-12-30T18:22:38.092050",
      "status": "active"
    },
    {
      "client_id": "V7V845U2-QQP5-4908-KKJG-97C872D0Y1YV",
      "username": "dftdbwuvq548",
      "discord_id": "1395017290289909790",
      "discord_name": "drehleiter232",
      "timestamp": "2025-12-30T18:45:59.747566",
      "status": "active"
    },
    {
      "client_id": "12Y4822W-7T0U-4S35-83L5-J300I45J4653",
      "username": "",
      "discord_id": "1280529967402319908",
      "discord_name": "fakepasha",
      "timestamp": "2025-12-30T20:23:58.900806",
      "status": "active"
    },
    {
      "client_id": "8XT2V5RO-2N9L-4J0I-878I-D032CC463AX4",
      "username": "q0ektk13",
      "discord_id": "1056685957925056573",
      "discord_name": "v0ltex.1",
      "timestamp": "2025-12-30T21:56:39.626300",
      "status": "active"
    },
    {
      "client_id": "0X76W902-3802-452T-9U67-06R948NK430L",
      "username": "Nmzcat3506",
      "discord_id": "1218609027919909015",
      "discord_name": "user004778",
      "timestamp": "2025-12-30T22:20:12.094821",
      "status": "active"
    },
    {
      "client_id": "64069398-YW17-4T1P-9NL0-J402LFG57B51",
      "username": "",
      "discord_id": "1094228889963864189",
      "discord_name": ".babo1234",
      "timestamp": "2025-12-31T00:33:36.053667",
      "status": "active"
    },
    {
      "client_id": "49W3XR90-61Q2-4R47-M2L2-H4K56G8732D6",
      "username": "Ghji_Zlgp011",
      "discord_id": "930168421889478706",
      "discord_name": "maximilian.fms",
      "timestamp": "2025-12-31T05:59:02.104823",
      "status": "active"
    },
    {
      "client_id": "ZTVSNOL6-245K-494G-D7D7-642235AXW294",
      "username": "ywus",
      "discord_id": "1392239904980734104",
      "discord_name": "fxrkan2sigma",
      "timestamp": "2025-12-31T06:58:31.559664",
      "status": "active"
    },
    {
      "client_id": "Zyvzbyr_7",
      "username": "9V4164Y7-4RRS-47P9-97L2-33I78J1708HE",
      "discord_id": "1170672247049027635",
      "discord_name": "r124r_",
      "timestamp": "2025-12-31T12:21:25.098621",
      "status": "active"
    },
    {
      "client_id": "XY57S45S-72Q0-4O2J-8942-160K3IICZZ37",
      "username": "",
      "discord_id": "1450629275848806541",
      "discord_name": "3335sdw",
      "timestamp": "2025-12-31T13:41:43.548230",
      "status": "active"
    }
  ]
}